src/code/music_player/beater/beater.v
module beater(
    input clk,
    input ready,
    input reset,
    output beat
);
    reg [2:0] q;
    always @(posedge clk) begin
        if (reset) begin
            q <= 3'b0;
        end else if (ready) begin
            if(q == 3'd7) q <= 0;
            else      q <= q + 1;
        end
    end
    assign beat = (q == 3'd7) & ready;
endmodule

src/testbench/beater.v
`timescale 1ns / 1ps

module beater_tb;

    // 输入信号
    reg clk;
    reg ready;
    reg reset;
    // 输出信号
    wire beat;
    
    // 实例化待测模块
    beater u_beater (
        .clk(clk),
        .ready(ready),
        .reset(reset),
        .beat(beat)
    );
    
    // 时钟：周期 10ns (100MHz)
    initial begin
        clk = 0;
        forever #5 clk = ~clk;
    end
    
    // 测试激励
    initial begin
        // 初始状态
        ready = 0;
        reset = 1;
        // 等待复位稳定
        repeat(3) @(posedge clk);
        reset = 0;

        // 测试1: ready=1，观察8个时钟周期的beat输出
        ready = 1;

        repeat(10) @(posedge clk);
        
        // 测试2: ready=0，停止计数，beat应为0
        ready = 0;
        repeat(5) @(posedge clk);
        
        // 测试3: 再次使能ready
        ready = 1;
        repeat(10) @(posedge clk);
        
        // 测试4: 短脉冲ready
        ready = 0;
        @(posedge clk);
        ready = 1;
        @(posedge clk);
        ready = 0;
        repeat(5) @(posedge clk);
        
        // 结束仿真
        $finish();
    end
    
    // 生成 VCD 波形文件
    initial begin
        $dumpfile("beater.vcd");
        $dumpvars(0, beater_tb);
    end
    
    // 监控信号变化
    initial begin
        $monitor("Time=%0t, clk=%b, ready=%b, q=%d, beat=%b", 
                  $time, clk, ready, u_beater.q, beat);
    end

endmodule

beater.vcd
$date
	Wed Apr 22 14:53:17 2026
$end
$version
	Icarus Verilog
$end
$timescale
	1ps
$end
$scope module beater_tb $end
$var wire 1 ! beat $end
$var reg 1 " clk $end
$var reg 1 # ready $end
$var reg 1 $ reset $end
$scope module u_beater $end
$var wire 1 ! beat $end
$var wire 1 " clk $end
$var wire 1 # ready $end
$var wire 1 $ reset $end
$var reg 3 % q [2:0] $end
$upscope $end
$upscope $end
$enddefinitions $end
$comment Show the parameter values. $end
$dumpall
$end
#0
$dumpvars
bx %
1$
0#
0"
0!
$end
#5000
b0 %
1"
#10000
0"
#15000
1"
#20000
0"
#25000
b1 %
1#
0$
1"
#30000
0"
#35000
b10 %
1"
#40000
0"
#45000
b11 %
1"
#50000
0"
#55000
b100 %
1"
#60000
0"
#65000
b101 %
1"
#70000
0"
#75000
b110 %
1"
#80000
0"
#85000
1!
b111 %
1"
#90000
0"
#95000
0!
b0 %
1"
#100000
0"
#105000
b1 %
1"
#110000
0"
#115000
b10 %
1"
#120000
0"
#125000
0#
1"
#130000
0"
#135000
1"
#140000
0"
#145000
1"
#150000
0"
#155000
1"
#160000
0"
#165000
1"
#170000
0"
#175000
1#
1"
#180000
0"
#185000
b11 %
1"
#190000
0"
#195000
b100 %
1"
#200000
0"
#205000
b101 %
1"
#210000
0"
#215000
b110 %
1"
#220000
0"
#225000
1!
b111 %
1"
#230000
0"
#235000
0!
b0 %
1"
#240000
0"
#245000
b1 %
1"
#250000
0"
#255000
b10 %
1"
#260000
0"
#265000
b11 %
1"
#270000
0"
#275000
b100 %
0#
1"
#280000
0"
#285000
b101 %
1#
1"
#290000
0"
#295000
b110 %
0#
1"
