src/code/music_player/song_reader/judge.v
module judge(
    input [5:0] duration,
    input co,
    input clk,
    output  song_done
);
    reg song_done_raw;
    always @(posedge clk) begin
        if(co) begin
            song_done_raw <= 1'b1;
        end
        else if(duration == 6'b 000000) begin
            song_done_raw <= 1'b1;
        end
        else begin
            song_done_raw <= 1'b0;
        end
    end
    reg q;
    always @(posedge clk) begin
        q <= song_done_raw;
    end

    assign song_done = song_done_raw & ~q;
endmodule

src/testbench/judge_tb.v
`timescale 1ns / 1ps

module judge_tb;

    // 输入信号
    reg [5:0] duration;
    reg co;
    reg clk;
    
    // 输出信号
    wire song_done;
    
    // 实例化待测模块
    judge u_judge (
        .duration(duration),
        .co(co),
        .clk(clk),
        .song_done(song_done)
    );
    
    // 时钟信号：周期 10ns (100MHz)
    initial begin
        clk = 0;
        forever #5 clk = ~clk;  // 5ns 翻转，周期10ns
    end
    
    // 测试激励
    initial begin
        // 初始化
        duration = 6'b000000;
        co = 1'b0;
        
        // 等待几个时钟周期
        repeat(3) @(posedge clk);
        
        // 测试1: duration为0，song_done应为1
        duration = 6'b000000;
        co = 1'b0;
        repeat(2) @(posedge clk);
        
        // 测试2: duration非0，co=0，song_done应为0
        duration = 6'b001010;  // 十进制10
        co = 1'b0;
        repeat(2) @(posedge clk);
        
        // 测试3: co=1，song_done应为1
        duration = 6'b001010;
        co = 1'b1;
        repeat(2) @(posedge clk);
        
        // 测试4: co=0，duration非0，song_done应为0
        co = 1'b0;
        repeat(2) @(posedge clk);
        
        // 测试5: duration从非0变为0
        duration = 6'b000000;
        repeat(2) @(posedge clk);
        
        // 结束仿真
        repeat(5) @(posedge clk);
        $finish();
    end
    
    // 打印波形信息（可选）
    initial begin
        $dumpfile("judge.vcd");
        $dumpvars(0, judge_tb);
    end
    
    // 监控信号变化（可选，用于调试）
    initial begin
        $monitor("Time=%0t, duration=%b, co=%b, song_done=%b", 
                  $time, duration, co, song_done);
    end

endmodule

judge.vcd
$date
	Wed Apr 22 14:28:59 2026
$end
$version
	Icarus Verilog
$end
$timescale
	1ps
$end
$scope module judge_tb $end
$var wire 1 ! song_done $end
$var reg 1 " clk $end
$var reg 1 # co $end
$var reg 6 $ duration [5:0] $end
$scope module u_judge $end
$var wire 1 " clk $end
$var wire 1 # co $end
$var wire 6 % duration [5:0] $end
$var wire 1 ! song_done $end
$var reg 1 & q $end
$var reg 1 ' song_done_raw $end
$upscope $end
$upscope $end
$enddefinitions $end
$comment Show the parameter values. $end
$dumpall
$end
#0
$dumpvars
x'
x&
b0 %
b0 $
0#
0"
x!
$end
#5000
1'
1"
#10000
0"
#15000
0!
1&
1"
#20000
0"
#25000
1"
#30000
0"
#35000
1"
#40000
0"
#45000
0'
b1010 $
b1010 %
1"
#50000
0"
#55000
0&
1"
#60000
0"
#65000
1!
1'
1#
1"
#70000
0"
#75000
0!
1&
1"
#80000
0"
#85000
0'
0#
1"
#90000
0"
#95000
0&
1"
#100000
0"
#105000
1!
1'
b0 $
b0 %
1"
#110000
0"
#115000
0!
1&
1"
