src/code/music_player/mcu/mcu_counter.v
module mcu_counter(
    input clk,
    input en,
    input reset,
    output reg [1:0] q
);
always @(posedge clk) begin
    if (reset)
        q <= 2'b00;
    else if (en)
        q <= q + 1;
end
endmodule

src/code/music_player/mcu/mcu_controller.v
module mcu_controller(
    input wire clk,
    input wire reset,
    input play_pause,
    input next,
    input song_done,
    output reg play,
    output reg reset_play,
    output reg NextSong
);
    parameter RESET = 2'b00, PLAY = 2'b01, PAUSE = 2'b10, NEXT = 2'b11;
    // State register
    reg [1:0] state, next_state;
    always @(posedge clk) begin
        if (reset)
            state <= RESET;
        else
            state <= next_state;
    end

    //状态转换和输出逻辑
    always @(*) begin
        //默认输出
        play = 0;
        reset_play = 0;
        NextSong = 0;
        case (state)
            RESET: begin
                next_state = PAUSE; //初始状态为PAUSE，等待用户操作
                play = 0;
                NextSong = 0;
                reset_play = 1; //重置播放状态以准备第一首歌
            end
            PLAY: begin
                play = 1;
                NextSong = 0;
                reset_play = 0;
                if (play_pause)
                    next_state = PAUSE;
                else if (next)
                    next_state = NEXT;
                else if (song_done)
                    next_state = RESET;
                else
                    next_state = PLAY;
            end
            PAUSE: begin
                play = 0;
                NextSong = 0;
                reset_play = 0;
                if (play_pause)
                    next_state = PLAY;
                else if (next)
                    next_state = NEXT;
                else
                    next_state = PAUSE;
            end
            NEXT: begin
                play = 0;
                NextSong = 1;
                reset_play = 1; //重置播放状态以准备下一首歌
                next_state = PLAY; //切换到PLAY状态以自动播放下一首歌
            end
            default: next_state = RESET;
        endcase
    end
endmodule

src/code/music_player/mcu/mcu.v
module mcu(
    input clk,
    input reset,
    input play_pause,
    input next,
    input song_done,
    output play,
    output reset_play,
    output [1:0] song
);
    // output declaration of module controller

    wire NextSong;
    
    mcu_controller #(
        .RESET 	(2'b00  ),
        .PLAY  	(2'b01  ),
        .PAUSE 	(2'b10  ),
        .NEXT  	(2'b11  ))
    u_controller(
        .clk        	(clk         ),
        .reset      	(reset       ),
        .play_pause 	(play_pause  ),
        .next       	(next        ),
        .song_done  	(song_done   ),
        .play       	(play        ),
        .reset_play 	(reset_play  ),
        .NextSong   	(NextSong    )
    );
    
    // output declaration of module counter
    
    mcu_counter u_counter(
        .clk   	(clk    ),
        .en    	(NextSong     ),
        .reset 	(reset  ),
        .q     	(song      )
    );
    
endmodule

src/testbench/mcu_tb.v
`timescale 1ns / 1ps

////////////////////////////////////////////////////////////////////////////////
// Company: qmj
// Engineer:zju

////////////////////////////////////////////////////////////////////////////////

module mcu_tb;
   parameter delay=10; 
	// Inputs
	reg clk;
	reg reset;
	reg play_pause;
	reg next;
	reg song_done;

	// Outputs
	wire play;
	wire [1:0] song;
	wire reset_play;

	// Instantiate the Unit Under Test (UUT)
	mcu uut (
		.clk(clk), 
		.reset(reset), 
		.play_pause(play_pause), 
		.next(next), 
		.play(play), 
		.song(song), 
		.reset_play(reset_play), 
		.song_done(song_done)
	);
 
	initial begin
		// Initialize Inputs
		clk = 0;
		reset = 1;
		play_pause = 0;
		next = 0;
		song_done = 0;

		// 
		#(delay*1.5+1) reset=0;
		#(delay)   play_pause = 1;
    #(delay)   play_pause = 0;
		#(delay*5) play_pause = 1;
		#(delay)   play_pause = 0;
		#(delay*5) play_pause = 1;
    #(delay)   play_pause = 0;
    #(delay*8) next = 1;		
    #(delay)   next = 0;		
    #(delay*8) song_done  = 1; 
    #(delay)    song_done  = 0;
    #(delay*2) play_pause = 1;
    #(delay)   play_pause = 0;
    #(delay*5) next = 1;		
    #(delay)   next = 0;
    #(delay*8) song_done  = 1; 
    #(delay)    song_done  = 0;
    #(delay*5) next = 1;		
    #(delay)   next = 0; 
    #(delay*5) next = 1;		
    #(delay)   next = 0;   
	#(delay*5)  $stop;	
	
	end
	// initial begin
	// 	$dumpfile("prj/vcd/mcu_tb.vcd");
	// 	$dumpvars(0,mcu_tb );
	// end
	//clock
  always 		#(delay/2) clk=~clk;
endmodule

sim/mcu/dump.vcd
$date
	Wed May 06 13:54:41 2026
$end
$version
	ModelSim Version 2020.1
$end
$timescale
	1ps
$end

$scope module mcu_tb $end
$var parameter 32 ! delay $end
$var reg 1 " clk $end
$var reg 1 # reset $end
$var reg 1 $ play_pause $end
$var reg 1 % next $end
$var reg 1 & song_done $end
$var wire 1 ' play $end
$var wire 1 ( song [1] $end
$var wire 1 ) song [0] $end
$var wire 1 * reset_play $end

$scope module uut $end
$var wire 1 + clk $end
$var wire 1 , reset $end
$var wire 1 - play_pause $end
$var wire 1 . next $end
$var wire 1 / song_done $end
$var wire 1 ' play $end
$var wire 1 * reset_play $end
$var wire 1 ( song [1] $end
$var wire 1 ) song [0] $end
$var wire 1 0 NextSong $end

$scope module u_controller $end
$var parameter 2 1 RESET $end
$var parameter 2 2 PLAY $end
$var parameter 2 3 PAUSE $end
$var parameter 2 4 NEXT $end
$var wire 1 + clk $end
$var wire 1 , reset $end
$var wire 1 - play_pause $end
$var wire 1 . next $end
$var wire 1 / song_done $end
$var reg 1 5 play $end
$var reg 1 6 reset_play $end
$var reg 1 7 NextSong $end
$var reg 2 8 state [1:0] $end
$var reg 2 9 next_state [1:0] $end
$upscope $end

$scope module u_counter $end
$var wire 1 + clk $end
$var wire 1 0 en $end
$var wire 1 , reset $end
$var reg 2 : q [1:0] $end
$upscope $end
$upscope $end
$upscope $end
$enddefinitions $end
#0
$dumpvars
0"
1#
0$
0%
0&
05
06
07
bx 8
b0 9
bx :
b1010 !
b0 1
b1 2
b10 3
b11 4
0'
x)
x(
0*
00
0/
0.
0-
1,
0+
$end
#5000
1"
1+
b0 8
b0 :
0)
0(
b10 9
16
1*
#10000
0"
0+
#15000
1"
1+
#16000
0#
0,
#20000
0"
0+
#25000
1"
1+
b10 8
06
0*
#26000
1$
1-
b1 9
#30000
0"
0+
#35000
1"
1+
b1 8
15
b10 9
1'
#36000
0$
0-
05
15
b1 9
#40000
0"
0+
#45000
1"
1+
#50000
0"
0+
#55000
1"
1+
#60000
0"
0+
#65000
1"
1+
#70000
0"
0+
#75000
1"
1+
#80000
0"
0+
#85000
1"
1+
#86000
1$
1-
05
15
b10 9
#90000
0"
0+
#95000
1"
1+
b10 8
05
b1 9
0'
#96000
0$
0-
b10 9
#100000
0"
0+
#105000
1"
1+
#110000
0"
0+
#115000
1"
1+
#120000
0"
0+
#125000
1"
1+
#130000
0"
0+
#135000
1"
1+
#140000
0"
0+
#145000
1"
1+
#146000
1$
1-
b1 9
#150000
0"
0+
#155000
1"
1+
b1 8
15
b10 9
1'
#156000
0$
0-
05
15
b1 9
#160000
0"
0+
#165000
1"
1+
#170000
0"
0+
#175000
1"
1+
#180000
0"
0+
#185000
1"
1+
#190000
0"
0+
#195000
1"
1+
#200000
0"
0+
#205000
1"
1+
#210000
0"
0+
#215000
1"
1+
#220000
0"
0+
#225000
1"
1+
#230000
0"
0+
#235000
1"
1+
#236000
1%
1.
05
15
b11 9
#240000
0"
0+
#245000
1"
1+
b11 8
05
17
16
b1 9
0'
10
1*
#246000
0%
0.
06
07
17
16
#250000
0"
0+
#255000
1"
1+
b1 8
b1 :
1)
06
07
15
0*
00
1'
#260000
0"
0+
#265000
1"
1+
#270000
0"
0+
#275000
1"
1+
#280000
0"
0+
#285000
1"
1+
#290000
0"
0+
#295000
1"
1+
#300000
0"
0+
#305000
1"
1+
#310000
0"
0+
#315000
1"
1+
#320000
0"
0+
#325000
1"
1+
#326000
1&
1/
05
15
b0 9
#330000
0"
0+
#335000
1"
1+
b0 8
05
b10 9
16
0'
1*
#336000
0&
0/
06
16
#340000
0"
0+
#345000
1"
1+
b10 8
06
0*
#350000
0"
0+
#355000
1"
1+
#356000
1$
1-
b1 9
#360000
0"
0+
#365000
1"
1+
b1 8
15
b10 9
1'
#366000
0$
0-
05
15
b1 9
#370000
0"
0+
#375000
1"
1+
#380000
0"
0+
#385000
1"
1+
#390000
0"
0+
#395000
1"
1+
#400000
0"
0+
#405000
1"
1+
#410000
0"
0+
#415000
1"
1+
#416000
1%
1.
05
15
b11 9
#420000
0"
0+
#425000
1"
1+
b11 8
05
17
16
b1 9
0'
10
1*
#426000
0%
0.
06
07
17
16
#430000
0"
0+
#435000
1"
1+
b1 8
b10 :
0)
1(
06
07
15
0*
00
1'
#440000
0"
0+
#445000
1"
1+
#450000
0"
0+
#455000
1"
1+
#460000
0"
0+
#465000
1"
1+
#470000
0"
0+
#475000
1"
1+
#480000
0"
0+
#485000
1"
1+
#490000
0"
0+
#495000
1"
1+
#500000
0"
0+
#505000
1"
1+
#506000
1&
1/
05
15
b0 9
#510000
0"
0+
#515000
1"
1+
b0 8
05
b10 9
16
0'
1*
#516000
0&
0/
06
16
#520000
0"
0+
#525000
1"
1+
b10 8
06
0*
#530000
0"
0+
#535000
1"
1+
#540000
0"
0+
#545000
1"
1+
#550000
0"
0+
#555000
1"
1+
#560000
0"
0+
#565000
1"
1+
#566000
1%
1.
b11 9
#570000
0"
0+
#575000
1"
1+
b11 8
17
16
b1 9
10
1*
#576000
0%
0.
06
07
17
16
#580000
0"
0+
#585000
1"
1+
b1 8
b11 :
1)
06
07
15
0*
00
1'
#590000
0"
0+
#595000
1"
1+
#600000
0"
0+
#605000
1"
1+
#610000
0"
0+
#615000
1"
1+
#620000
0"
0+
#625000
1"
1+
#626000
1%
1.
05
15
b11 9
#630000
0"
0+
#635000
1"
1+
b11 8
05
17
16
b1 9
0'
10
1*
#636000
0%
0.
06
07
17
16
#640000
0"
0+
#645000
1"
1+
b1 8
b0 :
0)
0(
06
07
15
0*
00
1'
