src/code/music_player/beater/beater.v
module beater
#(
    parameter n = 64, // 计数器的最大值，即每n个时钟周期输出一个beat。分频比
    parameter counter_bits = 6 // 计数器的位宽，应该满足2^counter_bits >= n
)
(
    input clk,
    input ready,
    input reset,
    output beat
);
    reg [counter_bits-1:0] q;
    always @(posedge clk) begin
        if (reset) begin
            q <= 0;
        end else if (ready) begin
            if(q == n-1) q <= 0;
            else      q <= q + 1;
        end
    end
    assign beat = (q == n-1) & ready;
endmodule

src/testbench/beater_tb.v
`timescale 1ns / 1ps

module beater_tb;

    // 输入信号
    reg clk;
    reg ready;
    reg reset;
    
    // output declaration of module beater
    wire beat;
    
    beater #(
        .n            	(3  ),
        .counter_bits 	(2   ))
    u_beater(
        .clk   	(clk    ),
        .ready 	(ready  ),
        .reset 	(reset  ),
        .beat  	(beat   )
    );
    
    // 时钟：周期 10ns (100MHz)
    initial begin
        clk = 0;
        forever #5 clk = ~clk;
    end
    
    // 测试激励
    initial begin
        // 初始状态
        ready = 0;
        reset = 1;
        // 等待复位稳定
        repeat(3) @(posedge clk);
        reset = 0;

        // 测试1: ready=1，观察8个时钟周期的beat输出
        ready = 1;

        repeat(10) @(posedge clk);
        
        // 测试2: ready=0，停止计数，beat应为0
        ready = 0;
        repeat(5) @(posedge clk);
        
        // 测试3: 再次使能ready
        ready = 1;
        repeat(10) @(posedge clk);
        
        // 测试4: 短脉冲ready
        ready = 0;
        @(posedge clk);
        ready = 1;
        @(posedge clk);
        ready = 0;
        repeat(5) @(posedge clk);
        
        // 结束仿真
        //$finish();
        $stop();
    end
    
    // 生成 VCD 波形文件
    // initial begin
    //     $dumpfile("prj/vcd/beater.vcd");
    //     $dumpvars(0, beater_tb);
    // end
    
    // 监控信号变化
    initial begin
        $monitor("Time=%0t, clk=%b, ready=%b, q=%d, beat=%b", 
                  $time, clk, ready, u_beater.q, beat);
    end

endmodule

sim/beater/dump.vcd
$date
	Wed May 06 20:21:51 2026
$end
$version
	ModelSim Version 2020.1
$end
$timescale
	1ps
$end

$scope module beater_tb $end
$var reg 1 ! clk $end
$var reg 1 " ready $end
$var reg 1 # reset $end
$var wire 1 $ beat $end

$scope module u_beater $end
$var parameter 32 % n $end
$var parameter 32 & counter_bits $end
$var wire 1 ' clk $end
$var wire 1 ( ready $end
$var wire 1 ) reset $end
$var wire 1 $ beat $end
$var reg 2 * q [1:0] $end
$upscope $end
$upscope $end
$enddefinitions $end
#0
$dumpvars
0!
0"
1#
bx *
b11 %
b10 &
0$
1)
0(
0'
$end
#5000
1!
1'
b0 *
#10000
0!
0'
#15000
1!
1'
#20000
0!
0'
#25000
1!
1'
0#
1"
0)
1(
#30000
0!
0'
#35000
1!
1'
b1 *
#40000
0!
0'
#45000
1!
1'
b10 *
1$
#50000
0!
0'
#55000
1!
1'
b0 *
0$
#60000
0!
0'
#65000
1!
1'
b1 *
#70000
0!
0'
#75000
1!
1'
b10 *
1$
#80000
0!
0'
#85000
1!
1'
b0 *
0$
#90000
0!
0'
#95000
1!
1'
b1 *
#100000
0!
0'
#105000
1!
1'
b10 *
1$
#110000
0!
0'
#115000
1!
1'
b0 *
0$
#120000
0!
0'
#125000
1!
1'
0"
0(
b1 *
#130000
0!
0'
#135000
1!
1'
#140000
0!
0'
#145000
1!
1'
#150000
0!
0'
#155000
1!
1'
#160000
0!
0'
#165000
1!
1'
#170000
0!
0'
#175000
1!
1'
1"
1(
#180000
0!
0'
#185000
1!
1'
b10 *
1$
#190000
0!
0'
#195000
1!
1'
b0 *
0$
#200000
0!
0'
#205000
1!
1'
b1 *
#210000
0!
0'
#215000
1!
1'
b10 *
1$
#220000
0!
0'
#225000
1!
1'
b0 *
0$
#230000
0!
0'
#235000
1!
1'
b1 *
#240000
0!
0'
#245000
1!
1'
b10 *
1$
#250000
0!
0'
#255000
1!
1'
b0 *
0$
#260000
0!
0'
#265000
1!
1'
b1 *
#270000
0!
0'
#275000
1!
1'
0"
0(
b10 *
#280000
0!
0'
#285000
1!
1'
1"
1(
1$
#290000
0!
0'
#295000
1!
1'
0"
0(
0$
b0 *
