src/code/music_player/mcu/mcu_counter.v
module mcu_counter(
    input clk,
    input en,
    input reset,
    output reg [1:0] q
);
always @(posedge clk) begin
    if (reset)
        q <= 2'b00;
    else if (en)
        q <= q + 1;
end
endmodule

src/code/music_player/mcu/mcu_controller.v
module mcu_controller(
    input wire clk,
    input wire reset,
    input play_pause,
    input next,
    input song_done,
    output reg play,
    output reg reset_play,
    output reg NextSong
);
    parameter RESET = 2'b00, PLAY = 2'b01, PAUSE = 2'b10, NEXT = 2'b11;
    // State register
    reg [1:0] state, next_state;
    always @(posedge clk) begin
        if (reset)
            state <= RESET;
        else
            state <= next_state;
    end

    //状态转换和输出逻辑
    always @(*) begin
        //默认输出
        play = 0;
        reset_play = 0;
        NextSong = 0;
        case (state)
            RESET: begin
                next_state = PAUSE; //初始状态为PAUSE，等待用户操作
                play = 0;
                NextSong = 0;
                reset_play = 1; //重置播放状态以准备第一首歌
            end
            PLAY: begin
                play = 1;
                NextSong = 0;
                reset_play = 0;
                if (play_pause)
                    next_state = PAUSE;
                else if (next)
                    next_state = NEXT;
                else if (song_done)
                    next_state = RESET;
                else
                    next_state = PLAY;
            end
            PAUSE: begin
                play = 0;
                NextSong = 0;
                reset_play = 0;
                if (play_pause)
                    next_state = PLAY;
                else if (next)
                    next_state = NEXT;
                else
                    next_state = PAUSE;
            end
            NEXT: begin
                play = 0;
                NextSong = 1;
                reset_play = 1; //重置播放状态以准备下一首歌
                next_state = PLAY; //切换到PLAY状态以自动播放下一首歌
            end
            default: next_state = RESET;
        endcase
    end
endmodule

src/code/music_player/mcu/mcu.v
module mcu(
    input clk,
    input reset,
    input play_pause,
    input next,
    input song_done,
    output play,
    output reset_play,
    output [1:0] song
);
    // output declaration of module controller

    wire NextSong;
    
    mcu_controller #(
        .RESET 	(2'b00  ),
        .PLAY  	(2'b01  ),
        .PAUSE 	(2'b10  ),
        .NEXT  	(2'b11  ))
    u_controller(
        .clk        	(clk         ),
        .reset      	(reset       ),
        .play_pause 	(play_pause  ),
        .next       	(next        ),
        .song_done  	(song_done   ),
        .play       	(play        ),
        .reset_play 	(reset_play  ),
        .NextSong   	(NextSong    )
    );
    
    // output declaration of module counter
    
    mcu_counter u_counter(
        .clk   	(clk    ),
        .en    	(NextSong     ),
        .reset 	(reset  ),
        .q     	(song      )
    );
    
endmodule

src/testbench/mcu_tb.v
`timescale 1ns / 1ps

////////////////////////////////////////////////////////////////////////////////
// Company: qmj
// Engineer:zju

////////////////////////////////////////////////////////////////////////////////

module mcu_tb;
   parameter delay=10; 
	// Inputs
	reg clk;
	reg reset;
	reg play_pause;
	reg next;
	reg song_done;

	// Outputs
	wire play;
	wire [1:0] song;
	wire reset_play;

	// Instantiate the Unit Under Test (UUT)
	mcu uut (
		.clk(clk), 
		.reset(reset), 
		.play_pause(play_pause), 
		.next(next), 
		.play(play), 
		.song(song), 
		.reset_play(reset_play), 
		.song_done(song_done)
	);
 
	initial begin
		// Initialize Inputs
		clk = 0;
		reset = 1;
		play_pause = 0;
		next = 0;
		song_done = 0;

		// 
		#(delay*1.5+1) reset=0;
		#(delay)   play_pause = 1;
    #(delay)   play_pause = 0;
		#(delay*5) play_pause = 1;
		#(delay)   play_pause = 0;
		#(delay*5) play_pause = 1;
    #(delay)   play_pause = 0;
    #(delay*8) next = 1;		
    #(delay)   next = 0;		
    #(delay*8) song_done  = 1; 
    #(delay)    song_done  = 0;
    #(delay*2) play_pause = 1;
    #(delay)   play_pause = 0;
    #(delay*5) next = 1;		
    #(delay)   next = 0;
    #(delay*8) song_done  = 1; 
    #(delay)    song_done  = 0;
    #(delay*5) next = 1;		
    #(delay)   next = 0; 
    #(delay*5) next = 1;		
    #(delay)   next = 0;   
	#(delay*5)  $stop;	
	
	end
	// initial begin
	// 	$dumpfile("prj/vcd/mcu_tb.vcd");
	// 	$dumpvars(0,mcu_tb );
	// end
	//clock
  always 		#(delay/2) clk=~clk;
endmodule

prj/vcd/mcu_tb.vcd
$date
	Wed May 06 13:47:58 2026
$end
$version
	Icarus Verilog
$end
$timescale
	1ps
$end
$scope module mcu_tb $end
$var wire 2 ! song [1:0] $end
$var wire 1 " reset_play $end
$var wire 1 # play $end
$var parameter 32 $ delay $end
$var reg 1 % clk $end
$var reg 1 & next $end
$var reg 1 ' play_pause $end
$var reg 1 ( reset $end
$var reg 1 ) song_done $end
$scope module uut $end
$var wire 1 % clk $end
$var wire 1 & next $end
$var wire 1 ' play_pause $end
$var wire 1 ( reset $end
$var wire 1 ) song_done $end
$var wire 2 * song [1:0] $end
$var wire 1 " reset_play $end
$var wire 1 # play $end
$var wire 1 + NextSong $end
$scope module u_controller $end
$var wire 1 % clk $end
$var wire 1 & next $end
$var wire 1 ' play_pause $end
$var wire 1 ( reset $end
$var wire 1 ) song_done $end
$var parameter 2 , NEXT $end
$var parameter 2 - PAUSE $end
$var parameter 2 . PLAY $end
$var parameter 2 / RESET $end
$var reg 1 + NextSong $end
$var reg 2 0 next_state [1:0] $end
$var reg 1 # play $end
$var reg 1 " reset_play $end
$var reg 2 1 state [1:0] $end
$upscope $end
$scope module u_counter $end
$var wire 1 % clk $end
$var wire 1 + en $end
$var wire 1 ( reset $end
$var reg 2 2 q [1:0] $end
$upscope $end
$upscope $end
$upscope $end
$enddefinitions $end
$comment Show the parameter values. $end
$dumpall
b0 /
b1 .
b10 -
b11 ,
b1010 $
$end
#0
$dumpvars
bx 2
bx 1
b0 0
0+
bx *
0)
1(
0'
0&
0%
0#
0"
bx !
$end
#5000
1"
b10 0
b0 1
b0 !
b0 *
b0 2
1%
#10000
0%
#15000
1%
#16000
0(
#20000
0%
#25000
0"
b10 1
1%
#26000
b1 0
1'
#30000
0%
#35000
b10 0
1#
b1 1
1%
#36000
b1 0
1#
0'
#40000
0%
#45000
1%
#50000
0%
#55000
1%
#60000
0%
#65000
1%
#70000
0%
#75000
1%
#80000
0%
#85000
1%
#86000
b10 0
1#
1'
#90000
0%
#95000
b1 0
0#
b10 1
1%
#96000
b10 0
0'
#100000
0%
#105000
1%
#110000
0%
#115000
1%
#120000
0%
#125000
1%
#130000
0%
#135000
1%
#140000
0%
#145000
1%
#146000
b1 0
1'
#150000
0%
#155000
b10 0
1#
b1 1
1%
#156000
b1 0
1#
0'
#160000
0%
#165000
1%
#170000
0%
#175000
1%
#180000
0%
#185000
1%
#190000
0%
#195000
1%
#200000
0%
#205000
1%
#210000
0%
#215000
1%
#220000
0%
#225000
1%
#230000
0%
#235000
1%
#236000
b11 0
1#
1&
#240000
0%
#245000
b1 0
1"
1+
0#
b11 1
1%
#246000
1+
1"
0&
#250000
0%
#255000
1#
0+
0"
b1 !
b1 *
b1 2
b1 1
1%
#260000
0%
#265000
1%
#270000
0%
#275000
1%
#280000
0%
#285000
1%
#290000
0%
#295000
1%
#300000
0%
#305000
1%
#310000
0%
#315000
1%
#320000
0%
#325000
1%
#326000
b0 0
1#
1)
#330000
0%
#335000
1"
b10 0
0#
b0 1
1%
#336000
1"
0)
#340000
0%
#345000
0"
b10 1
1%
#350000
0%
#355000
1%
#356000
b1 0
1'
#360000
0%
#365000
b10 0
1#
b1 1
1%
#366000
b1 0
1#
0'
#370000
0%
#375000
1%
#380000
0%
#385000
1%
#390000
0%
#395000
1%
#400000
0%
#405000
1%
#410000
0%
#415000
1%
#416000
b11 0
1#
1&
#420000
0%
#425000
b1 0
1"
1+
0#
b11 1
1%
#426000
1+
1"
0&
#430000
0%
#435000
1#
0+
0"
b10 !
b10 *
b10 2
b1 1
1%
#440000
0%
#445000
1%
#450000
0%
#455000
1%
#460000
0%
#465000
1%
#470000
0%
#475000
1%
#480000
0%
#485000
1%
#490000
0%
#495000
1%
#500000
0%
#505000
1%
#506000
b0 0
1#
1)
#510000
0%
#515000
1"
b10 0
0#
b0 1
1%
#516000
1"
0)
#520000
0%
#525000
0"
b10 1
1%
#530000
0%
#535000
1%
#540000
0%
#545000
1%
#550000
0%
#555000
1%
#560000
0%
#565000
1%
#566000
b11 0
1&
#570000
0%
#575000
b1 0
1"
1+
b11 1
1%
#576000
1+
1"
0&
#580000
0%
#585000
1#
0+
0"
b1 1
b11 !
b11 *
b11 2
1%
#590000
0%
#595000
1%
#600000
0%
#605000
1%
#610000
0%
#615000
1%
#620000
0%
#625000
1%
#626000
b11 0
1#
1&
#630000
0%
#635000
b1 0
1"
1+
0#
b11 1
1%
#636000
1+
1"
0&
#640000
0%
#645000
1#
0+
0"
b1 1
b0 !
b0 *
b0 2
1%
