src/code/music_player/syncer/syncer.v
module syncer(
    input clk,
    input in,
    output out
);
    reg q1,q2;
    always @(posedge clk) begin
        q1 <= in;
        q2 <= q1;
    end
    assign out = (~q2 & q1);
endmodule

src/testbench/syncer_tb.v
// tb_syncer.v
// Testbench for syncer module (edge detection / pulse generator)
// Function: synchronizes input and outputs a single-cycle pulse on rising edge

`timescale 1ns / 1ps

module syncer_tb();

    // Testbench signals
    reg clk;
    reg in;
    wire out;
    
    // Instantiate the module under test (MUT)
    syncer uut (
        .clk(clk),
        .in(in),
        .out(out)
    );
    
    // Clock generation: 100 MHz clock (period = 10 ns)
    always #5 clk = ~clk;
    
    // VCD dump for waveform viewing
    initial begin
        $dumpfile("prj/vcd/syncer_tb.vcd");
        $dumpvars(0, syncer_tb);
    end
    
    // Test sequence
    initial begin
        // Initialize signals
        clk = 0;
        in = 0;
        
        // Display test info
        $display("========================================");
        $display("Syncer Module Testbench");
        $display("Function: Rising edge detection with single-cycle pulse output");
        $display("========================================\n");
        
        // Wait for initial stabilization
        #20;
        
        // Test 1: Single short pulse (width < 1 clock cycle)
        $display("Test 1: Short pulse (15 ns wide, < 1 clock cycle)");
        @(posedge clk) #2;
        in = 1;
        #15;
        in = 0;
        #50;
        
        // Test 2: Single long pulse (width > 2 clock cycles)
        $display("\nTest 2: Long pulse (85 ns wide, > 2 clock cycles)");
        @(posedge clk) #2;
        in = 1;
        #85;
        in = 0;
        #50;
        
        // Test 3: Pulse exactly 1 clock cycle
        $display("\nTest 3: Exactly 1 clock cycle pulse (10 ns)");
        @(posedge clk) #2;
        in = 1;
        #10;
        in = 0;
        #50;
        
        //$finish;
        $stop();
    end

    
endmodule

prj/vcd/syncer_tb.vcd
$date
	Wed May 06 20:40:20 2026
$end
$version
	Icarus Verilog
$end
$timescale
	1ps
$end
$scope module syncer_tb $end
$var wire 1 ! out $end
$var reg 1 " clk $end
$var reg 1 # in $end
$scope module uut $end
$var wire 1 " clk $end
$var wire 1 # in $end
$var wire 1 ! out $end
$var reg 1 $ q1 $end
$var reg 1 % q2 $end
$upscope $end
$upscope $end
$enddefinitions $end
$comment Show the parameter values. $end
$dumpall
$end
#0
$dumpvars
x%
x$
0#
0"
x!
$end
#5000
0!
0$
1"
#10000
0"
#15000
0%
1"
#20000
0"
#25000
1"
#27000
1#
#30000
0"
#35000
1!
1$
1"
#40000
0"
#42000
0#
#45000
0!
1%
0$
1"
#50000
0"
#55000
0%
1"
#60000
0"
#65000
1"
#70000
0"
#75000
1"
#80000
0"
#85000
1"
#90000
0"
#95000
1"
#97000
1#
#100000
0"
#105000
1!
1$
1"
#110000
0"
#115000
0!
1%
1"
#120000
0"
#125000
1"
#130000
0"
#135000
1"
#140000
0"
#145000
1"
#150000
0"
#155000
1"
#160000
0"
#165000
1"
#170000
0"
#175000
1"
#180000
0"
#182000
0#
#185000
0$
1"
#190000
0"
#195000
0%
1"
#200000
0"
#205000
1"
#210000
0"
#215000
1"
#220000
0"
#225000
1"
#230000
0"
#235000
1"
#237000
1#
#240000
0"
#245000
1!
1$
1"
#247000
0#
#250000
0"
#255000
0!
1%
0$
1"
#260000
0"
#265000
0%
1"
