src/code/music_player/note_player/timer.v
module timer(
    input clk,
    input beat,
    input [5:0] duration_to_load,
    input timer_clear,
    output timer_done
);  
    reg [5:0] q;
    always @(posedge clk) begin
        if(timer_clear) begin
            q <= 0;
        end else if (beat) begin
            if( q == duration_to_load - 1) begin
                q <= 0;
            end else begin
                q <= q + 1;
            end
        end
    end
    assign timer_done = (q == duration_to_load - 1) & beat;
endmodule

src/testbench/timer_tb.v
`timescale 1ns / 1ps

module timer_tb;

    // 测试信号
    reg clk;
    reg beat;
    reg [5:0] duration_to_load;
    reg timer_clear;
    wire timer_done;
    
    // 实例化被测模块
    timer uut (
        .clk(clk),
        .beat(beat),
        .duration_to_load(duration_to_load),
        .timer_clear(timer_clear),
        .timer_done(timer_done)
    );
    
    // 时钟生成：周期 10ns (100MHz)
    initial begin
        clk = 0;
        forever #5 clk = ~clk;
    end
    
    // 测试激励
    initial begin
        // 初始化
        beat = 0;
        duration_to_load = 6'd10;  // 计数到10
        timer_clear = 1;
        
        // 显示波形开始
        $display("=== Timer Test Start ===");
        $dumpfile("prj/vcd/timer.vcd");
        $dumpvars(0, timer_tb);
        
        // 等待几个时钟周期
        repeat(2) @(posedge clk);
        
        // 释放 timer_clear，开始计时
        timer_clear = 0;
        $display("Time=%0t: Timer started, duration=%0d", $time, duration_to_load);
        
        // 测试1：正常计数到 duration_to_load
        repeat(10) begin
            @(posedge clk);
            beat = 1;  // 每个时钟周期都 beat
            $display("Time=%0t: q=%0d, timer_done=%0d", $time, uut.q, timer_done);
        end
        
        // 停止 beat
        @(posedge clk);
        beat = 0;
        $display("Time=%0t: Beat stopped, q=%0d", $time, uut.q);
        
        // 等待几拍
        repeat(3) @(posedge clk);
        
        // 测试2：重新开始计时（timer_clear）
        timer_clear = 1;
        @(posedge clk);
        timer_clear = 0;
        duration_to_load = 6'd5;  // 改为计数到5
        $display("Time=%0t: Restart timer, new duration=%0d", $time, duration_to_load);
        
        // 继续计数
        repeat(6) begin
            @(posedge clk);
            beat = 1;
            $display("Time=%0t: q=%0d, timer_done=%0d", $time, uut.q, timer_done);
        end
        
        // 测试3：中间清零
        beat = 0;
        @(posedge clk);
        timer_clear = 1;
        @(posedge clk);
        timer_clear = 0;
        duration_to_load = 6'd8;
        beat = 1;
        $display("Time=%0t: Reset mid-way, duration=%0d", $time, duration_to_load);
        
        repeat(10) begin
            @(posedge clk);
            $display("Time=%0t: q=%0d, timer_done=%0d", $time, uut.q, timer_done);
        end
        
        // 测试4：边界条件 - duration_to_load = 1
        timer_clear = 1;
        @(posedge clk);
        timer_clear = 0;
        duration_to_load = 6'd1;
        beat = 1;
        $display("Time=%0t: Edge case - duration=1", $time);
        
        @(posedge clk);
        $display("Time=%0t: q=%0d, timer_done=%0d", $time, uut.q, timer_done);
        
        @(posedge clk);
        $display("Time=%0t: q=%0d, timer_done=%0d", $time, uut.q, timer_done);
        
        // 测试结束
        repeat(5) @(posedge clk);
        $display("=== Timer Test Complete ===");
        $finish;
    end
    
    // 监控 timer_done 变化
    always @(posedge timer_done) begin
        $display("Time=%0t: *** TIMER DONE ASSERTED ***", $time);
    end
    

endmodule

prj/vcd/timer.vcd
$date
	Fri Apr 17 08:37:01 2026
$end
$version
	Icarus Verilog
$end
$timescale
	1ps
$end
$scope module timer_tb $end
$var wire 1 ! timer_done $end
$var reg 1 " beat $end
$var reg 1 # clk $end
$var reg 6 $ duration_to_load [5:0] $end
$var reg 1 % timer_clear $end
$scope module uut $end
$var wire 1 " beat $end
$var wire 1 # clk $end
$var wire 6 & duration_to_load [5:0] $end
$var wire 1 % timer_clear $end
$var wire 1 ! timer_done $end
$var reg 6 ' q [5:0] $end
$upscope $end
$upscope $end
$enddefinitions $end
$comment Show the parameter values. $end
$dumpall
$end
#0
$dumpvars
bx '
b1010 &
1%
b1010 $
0#
0"
0!
$end
#5000
b0 '
1#
#10000
0#
#15000
0%
1#
#20000
0#
#25000
b1 '
1"
1#
#30000
0#
#35000
b10 '
1#
#40000
0#
#45000
b11 '
1#
#50000
0#
#55000
b100 '
1#
#60000
0#
#65000
b101 '
1#
#70000
0#
#75000
b110 '
1#
#80000
0#
#85000
b111 '
1#
#90000
0#
#95000
b1000 '
1#
#100000
0#
#105000
1!
b1001 '
1#
#110000
0#
#115000
0!
b0 '
1#
#120000
0#
#125000
0"
1#
#130000
0#
#135000
1#
#140000
0#
#145000
1#
#150000
0#
#155000
1%
1#
#160000
0#
#165000
b101 $
b101 &
0%
1#
#170000
0#
#175000
1"
1#
#180000
0#
#185000
b1 '
1#
#190000
0#
#195000
b10 '
1#
#200000
0#
#205000
b11 '
1#
#210000
0#
#215000
1!
b100 '
1#
#220000
0#
#225000
0!
0"
1#
#230000
0#
#235000
1%
1#
#240000
0#
#245000
b101 '
1"
b1000 $
b1000 &
0%
1#
#250000
0#
#255000
b110 '
1#
#260000
0#
#265000
1!
b111 '
1#
#270000
0#
#275000
0!
b0 '
1#
#280000
0#
#285000
b1 '
1#
#290000
0#
#295000
b10 '
1#
#300000
0#
#305000
b11 '
1#
#310000
0#
#315000
b100 '
1#
#320000
0#
#325000
b101 '
1#
#330000
0#
#335000
b110 '
1#
#340000
0#
#345000
b0 '
1%
1#
#350000
0#
#355000
1!
b1 $
b1 &
0%
1#
